MANIFEST.in
create_pkg.py
setup.py
django_app_skeleton.egg-info/PKG-INFO
django_app_skeleton.egg-info/SOURCES.txt
django_app_skeleton.egg-info/dependency_links.txt
django_app_skeleton.egg-info/top_level.txt
skel/CHANGELOG
skel/LICENSE
skel/MANIFEST.in
skel/README.rst
skel/gitignore
skel/requirements.txt
skel/setup.py
skel/app_name/__init__.py
skel/app_name/admin.py
skel/app_name/forms.py
skel/app_name/models.py
skel/app_name/settings.py
skel/app_name/tests.py
skel/app_name/urls.py
skel/app_name/views.py
skel/app_name/static/app_name/placeholder.txt
skel/app_name/templates/app_name/placeholder.txt
skel/app_name/templatetags/__init__.py
skel/app_name/templatetags/app_name_tags.py
skel/doc_src/Makefile
skel/doc_src/conf.py
skel/doc_src/getting_started.rst
skel/doc_src/index.rst
skel/doc_src/installation.rst
skel/doc_src/make.bat
skel/doc_src/_static/breadcrumb_background.png
skel/doc_src/_static/default.css
skel/doc_src/_static/documentation.png
skel/doc_src/_static/header_sm_mid.png
skel/doc_src/_static/scrn1.png
skel/doc_src/_static/scrn2.png
skel/doc_src/_static/searchfield_leftcap.png
skel/doc_src/_static/searchfield_repeat.png
skel/doc_src/_static/searchfield_rightcap.png
skel/doc_src/_static/title_background.png
skel/doc_src/_static/toc.js
skel/doc_src/_static/triangle_closed.png
skel/doc_src/_static/triangle_left.png
skel/doc_src/_static/triangle_open.png
skel/doc_src/_templates/layout.html
skel/doc_src/reference/index.rst
skel/doc_src/reference/models.rst
skel/doc_src/reference/settings.rst
skel/example/__init__.py
skel/example/manage.py
skel/example/settings.py
skel/example/urls.py
skel/example/wsgi.py
skel/example/simpleapp/__init__.py
skel/example/simpleapp/admin.py
skel/example/simpleapp/models.py
skel/example/simpleapp/urls.py
skel/example/simpleapp/templates/simpleapp/simplemodel_detail.html
skel/example/simpleapp/templates/simpleapp/simplemodel_list.html
skel/example/templates/base.html