Metadata-Version: 1.0
Name: django-app-skeleton
Version: 1.0.4
Summary: A basic skeleton and script to make a packageable django application
Home-page: https://github.com/callowayproject/django-app-skeleton
Author: Calloway Project
Author-email: webmaster@callowayproject.com
License: UNKNOWN
Platform: UNKNOWN
Classifier: Framework :: Django
